odoo/addons/account_invoice_supplier_ref_unique/README.rst
odoo/addons/account_invoice_supplier_ref_unique/__init__.py
odoo/addons/account_invoice_supplier_ref_unique/__manifest__.py
odoo/addons/account_invoice_supplier_ref_unique/i18n/account_invoice_supplier_ref_unique.pot
odoo/addons/account_invoice_supplier_ref_unique/i18n/ar.po
odoo/addons/account_invoice_supplier_ref_unique/i18n/bg.po
odoo/addons/account_invoice_supplier_ref_unique/i18n/bs.po
odoo/addons/account_invoice_supplier_ref_unique/i18n/ca.po
odoo/addons/account_invoice_supplier_ref_unique/i18n/cs.po
odoo/addons/account_invoice_supplier_ref_unique/i18n/de.po
odoo/addons/account_invoice_supplier_ref_unique/i18n/el_GR.po
odoo/addons/account_invoice_supplier_ref_unique/i18n/en_GB.po
odoo/addons/account_invoice_supplier_ref_unique/i18n/es.po
odoo/addons/account_invoice_supplier_ref_unique/i18n/es_CR.po
odoo/addons/account_invoice_supplier_ref_unique/i18n/es_EC.po
odoo/addons/account_invoice_supplier_ref_unique/i18n/es_ES.po
odoo/addons/account_invoice_supplier_ref_unique/i18n/es_MX.po
odoo/addons/account_invoice_supplier_ref_unique/i18n/et.po
odoo/addons/account_invoice_supplier_ref_unique/i18n/fi.po
odoo/addons/account_invoice_supplier_ref_unique/i18n/fr.po
odoo/addons/account_invoice_supplier_ref_unique/i18n/fr_CA.po
odoo/addons/account_invoice_supplier_ref_unique/i18n/fr_CH.po
odoo/addons/account_invoice_supplier_ref_unique/i18n/gl.po
odoo/addons/account_invoice_supplier_ref_unique/i18n/hr.po
odoo/addons/account_invoice_supplier_ref_unique/i18n/hr_HR.po
odoo/addons/account_invoice_supplier_ref_unique/i18n/hu.po
odoo/addons/account_invoice_supplier_ref_unique/i18n/id.po
odoo/addons/account_invoice_supplier_ref_unique/i18n/it.po
odoo/addons/account_invoice_supplier_ref_unique/i18n/ja.po
odoo/addons/account_invoice_supplier_ref_unique/i18n/lt.po
odoo/addons/account_invoice_supplier_ref_unique/i18n/mk.po
odoo/addons/account_invoice_supplier_ref_unique/i18n/mn.po
odoo14_addon_account_invoice_supplier_ref_unique-14.0.1.0.1.dev7.dist-info/METADATA
odoo14_addon_account_invoice_supplier_ref_unique-14.0.1.0.1.dev7.dist-info/WHEEL
odoo14_addon_account_invoice_supplier_ref_unique-14.0.1.0.1.dev7.dist-info/top_level.txt
odoo14_addon_account_invoice_supplier_ref_unique-14.0.1.0.1.dev7.dist-info/RECORD
